wtinfo/__init__.py
wtinfo-0.1.0.dist-info/METADATA
wtinfo-0.1.0.dist-info/WHEEL
wtinfo-0.1.0.dist-info/RECORD
