Metadata-Version: 2.1
Name: wtinfo
Version: 0.1.0
Summary: Webtoon Information Scraper
License: MIT
Author: ilotoki0804
Author-email: ilotoki0804@gmail.com
Requires-Python: >=3.10,<4.0
Classifier: License :: OSI Approved :: MIT License
Classifier: Programming Language :: Python :: 3
Classifier: Programming Language :: Python :: 3.10
Classifier: Programming Language :: Python :: 3.11
Classifier: Programming Language :: Python :: 3.12
